{
  "annotations": {
    "list": [
      {
        "builtIn": 1,
        "datasource": {
          "type": "grafana",
          "uid": "-- Grafana --"
        },
        "enable": true,
        "hide": true,
        "iconColor": "rgba(0, 211, 255, 1)",
        "name": "Annotations & Alerts",
        "type": "dashboard"
      }
    ]
  },
  "editable": true,
  "fiscalYearStartMonth": 0,
  "graphTooltip": 0,
  "id": 4,
  "links": [],
  "panels": [
    {
      "collapsed": false,
      "gridPos": {
        "h": 1,
        "w": 24,
        "x": 0,
        "y": 0
      },
      "id": 103,
      "panels": [],
      "title": "💻 System Saturation (CPU, Memory, Disk)",
      "type": "row"
    },
    {
      "datasource": {
        "type": "prometheus",
        "uid": "prometheus"
      },
      "fieldConfig": {
        "defaults": {
          "color": {
            "mode": "palette-classic"
          },
          "custom": {
            "axisBorderShow": false,
            "axisCenteredZero": false,
            "axisColorMode": "text",
            "axisLabel": "",
            "axisPlacement": "auto",
            "barAlignment": 0,
            "barWidthFactor": 0.6,
            "drawStyle": "line",
            "fillOpacity": 20,
            "gradientMode": "opacity",
            "hideFrom": {
              "legend": false,
              "tooltip": false,
              "viz": false
            },
            "insertNulls": false,
            "lineInterpolation": "smooth",
            "lineWidth": 2,
            "pointSize": 5,
            "scaleDistribution": {
              "type": "linear"
            },
            "showPoints": "never",
            "showValues": false,
            "spanNulls": false,
            "stacking": {
              "group": "A",
              "mode": "none"
            },
            "thresholdsStyle": {
              "mode": "line"
            }
          },
          "mappings": [],
          "max": 100,
          "min": 0,
          "thresholds": {
            "mode": "absolute",
            "steps": [
              {
                "color": "green",
                "value": 0
              },
              {
                "color": "yellow",
                "value": 70
              },
              {
                "color": "red",
                "value": 85
              }
            ]
          },
          "unit": "percent"
        },
        "overrides": []
      },
      "gridPos": {
        "h": 8,
        "w": 8,
        "x": 0,
        "y": 1
      },
      "id": 30,
      "options": {
        "legend": {
          "calcs": [
            "mean",
            "max"
          ],
          "displayMode": "table",
          "placement": "bottom",
          "showLegend": true
        },
        "tooltip": {
          "hideZeros": false,
          "mode": "multi",
          "sort": "none"
        }
      },
      "pluginVersion": "12.3.0",
      "targets": [
        {
          "datasource": {
            "type": "prometheus",
            "uid": "prometheus"
          },
          "expr": "100 - (avg(rate(node_cpu_seconds_total{mode=\"idle\"}[5m])) * 100)",
          "legendFormat": "CPU Usage",
          "refId": "A"
        }
      ],
      "title": "CPU Usage %",
      "type": "timeseries"
    },
    {
      "datasource": {
        "type": "prometheus",
        "uid": "prometheus"
      },
      "fieldConfig": {
        "defaults": {
          "color": {
            "mode": "palette-classic"
          },
          "custom": {
            "axisBorderShow": false,
            "axisCenteredZero": false,
            "axisColorMode": "text",
            "axisLabel": "",
            "axisPlacement": "auto",
            "barAlignment": 0,
            "barWidthFactor": 0.6,
            "drawStyle": "line",
            "fillOpacity": 20,
            "gradientMode": "opacity",
            "hideFrom": {
              "legend": false,
              "tooltip": false,
              "viz": false
            },
            "insertNulls": false,
            "lineInterpolation": "smooth",
            "lineWidth": 2,
            "pointSize": 5,
            "scaleDistribution": {
              "type": "linear"
            },
            "showPoints": "never",
            "showValues": false,
            "spanNulls": false,
            "stacking": {
              "group": "A",
              "mode": "none"
            },
            "thresholdsStyle": {
              "mode": "line"
            }
          },
          "mappings": [],
          "max": 100,
          "min": 0,
          "thresholds": {
            "mode": "absolute",
            "steps": [
              {
                "color": "green",
                "value": 0
              },
              {
                "color": "yellow",
                "value": 75
              },
              {
                "color": "red",
                "value": 85
              }
            ]
          },
          "unit": "percent"
        },
        "overrides": []
      },
      "gridPos": {
        "h": 8,
        "w": 8,
        "x": 8,
        "y": 1
      },
      "id": 31,
      "options": {
        "legend": {
          "calcs": [
            "mean",
            "max"
          ],
          "displayMode": "table",
          "placement": "bottom",
          "showLegend": true
        },
        "tooltip": {
          "hideZeros": false,
          "mode": "multi",
          "sort": "none"
        }
      },
      "pluginVersion": "12.3.0",
      "targets": [
        {
          "datasource": {
            "type": "prometheus",
            "uid": "prometheus"
          },
          "expr": "(1 - (node_memory_MemAvailable_bytes / node_memory_MemTotal_bytes)) * 100",
          "legendFormat": "Memory Usage",
          "refId": "A"
        }
      ],
      "title": "Memory Usage %",
      "type": "timeseries"
    },
    {
      "datasource": {
        "type": "prometheus",
        "uid": "prometheus"
      },
      "fieldConfig": {
        "defaults": {
          "color": {
            "mode": "palette-classic"
          },
          "custom": {
            "axisBorderShow": false,
            "axisCenteredZero": false,
            "axisColorMode": "text",
            "axisLabel": "",
            "axisPlacement": "auto",
            "barAlignment": 0,
            "barWidthFactor": 0.6,
            "drawStyle": "line",
            "fillOpacity": 20,
            "gradientMode": "opacity",
            "hideFrom": {
              "legend": false,
              "tooltip": false,
              "viz": false
            },
            "insertNulls": false,
            "lineInterpolation": "smooth",
            "lineWidth": 2,
            "pointSize": 5,
            "scaleDistribution": {
              "type": "linear"
            },
            "showPoints": "never",
            "showValues": false,
            "spanNulls": false,
            "stacking": {
              "group": "A",
              "mode": "none"
            },
            "thresholdsStyle": {
              "mode": "line"
            }
          },
          "mappings": [],
          "max": 100,
          "min": 0,
          "thresholds": {
            "mode": "absolute",
            "steps": [
              {
                "color": "green",
                "value": 0
              },
              {
                "color": "yellow",
                "value": 70
              },
              {
                "color": "red",
                "value": 80
              }
            ]
          },
          "unit": "percent"
        },
        "overrides": []
      },
      "gridPos": {
        "h": 8,
        "w": 8,
        "x": 16,
        "y": 1
      },
      "id": 32,
      "options": {
        "legend": {
          "calcs": [
            "mean",
            "max"
          ],
          "displayMode": "table",
          "placement": "bottom",
          "showLegend": true
        },
        "tooltip": {
          "hideZeros": false,
          "mode": "multi",
          "sort": "none"
        }
      },
      "pluginVersion": "12.3.0",
      "targets": [
        {
          "datasource": {
            "type": "prometheus",
            "uid": "prometheus"
          },
          "expr": "(1 - (node_filesystem_avail_bytes{mountpoint=\"/\"} / node_filesystem_size_bytes{mountpoint=\"/\"})) * 100",
          "legendFormat": "Disk Usage",
          "refId": "A"
        }
      ],
      "title": "Disk Usage %",
      "type": "timeseries"
    },
    {
      "collapsed": false,
      "gridPos": {
        "h": 1,
        "w": 24,
        "x": 0,
        "y": 9
      },
      "id": 102,
      "panels": [],
      "title": "📊 Detailed Metrics - Traffic & Errors",
      "type": "row"
    },
    {
      "datasource": {
        "type": "prometheus",
        "uid": "prometheus"
      },
      "fieldConfig": {
        "defaults": {
          "color": {
            "mode": "palette-classic"
          },
          "custom": {
            "axisBorderShow": false,
            "axisCenteredZero": false,
            "axisColorMode": "text",
            "axisLabel": "",
            "axisPlacement": "auto",
            "barAlignment": 0,
            "barWidthFactor": 0.6,
            "drawStyle": "line",
            "fillOpacity": 20,
            "gradientMode": "none",
            "hideFrom": {
              "legend": false,
              "tooltip": false,
              "viz": false
            },
            "insertNulls": false,
            "lineInterpolation": "smooth",
            "lineWidth": 2,
            "pointSize": 5,
            "scaleDistribution": {
              "type": "linear"
            },
            "showPoints": "never",
            "showValues": false,
            "spanNulls": false,
            "stacking": {
              "group": "A",
              "mode": "normal"
            },
            "thresholdsStyle": {
              "mode": "off"
            }
          },
          "mappings": [],
          "thresholds": {
            "mode": "absolute",
            "steps": [
              {
                "color": "green",
                "value": 0
              }
            ]
          },
          "unit": "reqps"
        },
        "overrides": [
          {
            "matcher": {
              "id": "byName",
              "options": "5xx"
            },
            "properties": [
              {
                "id": "color",
                "value": {
                  "fixedColor": "red",
                  "mode": "fixed"
                }
              }
            ]
          },
          {
            "matcher": {
              "id": "byName",
              "options": "4xx"
            },
            "properties": [
              {
                "id": "color",
                "value": {
                  "fixedColor": "yellow",
                  "mode": "fixed"
                }
              }
            ]
          },
          {
            "matcher": {
              "id": "byName",
              "options": "2xx"
            },
            "properties": [
              {
                "id": "color",
                "value": {
                  "fixedColor": "green",
                  "mode": "fixed"
                }
              }
            ]
          }
        ]
      },
      "gridPos": {
        "h": 8,
        "w": 12,
        "x": 0,
        "y": 10
      },
      "id": 20,
      "options": {
        "legend": {
          "calcs": [
            "mean",
            "max"
          ],
          "displayMode": "table",
          "placement": "bottom",
          "showLegend": true
        },
        "tooltip": {
          "hideZeros": false,
          "mode": "multi",
          "sort": "desc"
        }
      },
      "pluginVersion": "12.3.0",
      "targets": [
        {
          "datasource": {
            "type": "prometheus",
            "uid": "prometheus"
          },
          "expr": "sum(rate(ktor_http_server_requests_seconds_count{status=~\"2..\"}[5m]))",
          "legendFormat": "2xx (Success)",
          "refId": "A"
        },
        {
          "datasource": {
            "type": "prometheus",
            "uid": "prometheus"
          },
          "expr": "sum(rate(ktor_http_server_requests_seconds_count{status=~\"4..\"}[5m]))",
          "legendFormat": "4xx (Client Error)",
          "refId": "B"
        },
        {
          "datasource": {
            "type": "prometheus",
            "uid": "prometheus"
          },
          "expr": "sum(rate(ktor_http_server_requests_seconds_count{status=~\"5..\"}[5m]))",
          "legendFormat": "5xx (Server Error)",
          "refId": "C"
        }
      ],
      "title": "Request Rate by Status Code",
      "type": "timeseries"
    },
    {
      "datasource": {
        "type": "prometheus",
        "uid": "prometheus"
      },
      "fieldConfig": {
        "defaults": {
          "color": {
            "mode": "palette-classic"
          },
          "custom": {
            "axisBorderShow": false,
            "axisCenteredZero": false,
            "axisColorMode": "text",
            "axisLabel": "",
            "axisPlacement": "auto",
            "barAlignment": 0,
            "barWidthFactor": 0.6,
            "drawStyle": "line",
            "fillOpacity": 10,
            "gradientMode": "none",
            "hideFrom": {
              "legend": false,
              "tooltip": false,
              "viz": false
            },
            "insertNulls": false,
            "lineInterpolation": "linear",
            "lineWidth": 2,
            "pointSize": 5,
            "scaleDistribution": {
              "type": "linear"
            },
            "showPoints": "never",
            "showValues": false,
            "spanNulls": false,
            "stacking": {
              "group": "A",
              "mode": "none"
            },
            "thresholdsStyle": {
              "mode": "line"
            }
          },
          "mappings": [],
          "max": 100,
          "min": 0,
          "thresholds": {
            "mode": "absolute",
            "steps": [
              {
                "color": "green",
                "value": 0
              },
              {
                "color": "red",
                "value": 1
              }
            ]
          },
          "unit": "percent"
        },
        "overrides": []
      },
      "gridPos": {
        "h": 8,
        "w": 12,
        "x": 12,
        "y": 10
      },
      "id": 21,
      "options": {
        "legend": {
          "calcs": [
            "mean",
            "max"
          ],
          "displayMode": "table",
          "placement": "bottom",
          "showLegend": true
        },
        "tooltip": {
          "hideZeros": false,
          "mode": "multi",
          "sort": "none"
        }
      },
      "pluginVersion": "12.3.0",
      "targets": [
        {
          "datasource": {
            "type": "prometheus",
            "uid": "prometheus"
          },
          "expr": "(sum(rate(ktor_http_server_requests_seconds_count{status=~\"5..\"}[5m])) / sum(rate(ktor_http_server_requests_seconds_count[5m]))) * 100",
          "legendFormat": "Error Rate (5xx)",
          "refId": "A"
        }
      ],
      "title": "Error Rate % (SLO: < 1%)",
      "type": "timeseries"
    },
    {
      "collapsed": false,
      "gridPos": {
        "h": 1,
        "w": 24,
        "x": 0,
        "y": 18
      },
      "id": 100,
      "panels": [],
      "title": "📊 Four Golden Signals - INT531 SRE Monitoring",
      "type": "row"
    },
    {
      "collapsed": false,
      "gridPos": {
        "h": 1,
        "w": 24,
        "x": 0,
        "y": 1
      },
      "id": 200,
      "panels": [],
      "title": "📱 Frontend - Four Golden Signals (Nginx)",
      "type": "row"
    },
    {
      "datasource": {
        "type": "prometheus",
        "uid": "prometheus"
      },
      "description": "**Why Monitor This?**\nLatency is critical for user experience. High latency indicates performance issues that directly impact user satisfaction. This measures the end-to-end request latency from the frontend proxy to backend.\n\n**What It Measures:**\nP95 response time of requests proxied through Nginx to the backend. This represents the latency experienced by 95% of users.\n\n**Note:** Standard nginx-exporter (stub_status) doesn't provide latency metrics, so we measure the backend response time which reflects the total latency from Nginx's perspective.",
      "fieldConfig": {
        "defaults": {
          "color": {
            "mode": "thresholds"
          },
          "mappings": [],
          "thresholds": {
            "mode": "absolute",
            "steps": [
              {
                "color": "green",
                "value": 0
              },
              {
                "color": "yellow",
                "value": 0.2
              },
              {
                "color": "red",
                "value": 0.5
              }
            ]
          },
          "unit": "s"
        },
        "overrides": []
      },
      "gridPos": {
        "h": 8,
        "w": 6,
        "x": 0,
        "y": 19
      },
      "id": 210,
      "options": {
        "minVizHeight": 75,
        "minVizWidth": 75,
        "orientation": "auto",
        "reduceOptions": {
          "calcs": [
            "lastNotNull"
          ],
          "fields": "",
          "values": false
        },
        "showThresholdLabels": false,
        "showThresholdMarkers": true,
        "sizing": "auto"
      },
      "pluginVersion": "12.3.0",
      "targets": [
        {
          "datasource": {
            "type": "prometheus",
            "uid": "prometheus"
          },
          "expr": "max(ktor_http_server_requests_seconds{quantile='0.95'}) or vector(0)",
          "legendFormat": "P95 Latency",
          "refId": "A"
        }
      ],
      "title": "🕐 Latency (Frontend→Backend P95)",
      "type": "gauge"
    },
    {
      "datasource": {
        "type": "prometheus",
        "uid": "prometheus"
      },
      "description": "**Why Monitor This?**\nRequest rate indicates user traffic patterns and helps identify traffic spikes or drops. This is crucial for capacity planning and detecting anomalies in user behavior.\n\n**What It Measures:**\nTotal HTTP requests per second handled by Nginx frontend proxy.",
      "fieldConfig": {
        "defaults": {
          "color": {
            "mode": "thresholds"
          },
          "mappings": [],
          "thresholds": {
            "mode": "absolute",
            "steps": [
              {
                "color": "green",
                "value": 0
              },
              {
                "color": "yellow",
                "value": 50
              },
              {
                "color": "red",
                "value": 100
              }
            ]
          },
          "unit": "reqps"
        },
        "overrides": []
      },
      "gridPos": {
        "h": 8,
        "w": 6,
        "x": 6,
        "y": 1
      },
      "id": 201,
      "options": {
        "minVizHeight": 75,
        "minVizWidth": 75,
        "orientation": "auto",
        "reduceOptions": {
          "calcs": [
            "lastNotNull"
          ],
          "fields": "",
          "values": false
        },
        "showThresholdLabels": false,
        "showThresholdMarkers": true,
        "sizing": "auto"
      },
      "pluginVersion": "12.3.0",
      "targets": [
        {
          "datasource": {
            "type": "prometheus",
            "uid": "prometheus"
          },
          "expr": "rate(nginx_http_requests_total[5m])",
          "legendFormat": "Frontend Traffic",
          "refId": "A"
        }
      ],
      "title": "📈 Traffic (Frontend Requests/sec)",
      "type": "gauge"
    },
    {
      "datasource": {
        "type": "prometheus",
        "uid": "prometheus"
      },
      "description": "**Why Monitor This?**\nActive connections show current load on the frontend. High active connections can indicate capacity issues or the need to scale. This helps predict when resources will be exhausted.\n\n**What It Measures:**\nCurrent number of active client connections to Nginx, including connections that are reading, writing, or waiting.",
      "fieldConfig": {
        "defaults": {
          "color": {
            "mode": "thresholds"
          },
          "mappings": [],
          "thresholds": {
            "mode": "absolute",
            "steps": [
              {
                "color": "green",
                "value": 0
              },
              {
                "color": "yellow",
                "value": 100
              },
              {
                "color": "red",
                "value": 200
              }
            ]
          },
          "unit": "short"
        },
        "overrides": []
      },
      "gridPos": {
        "h": 8,
        "w": 6,
        "x": 12,
        "y": 1
      },
      "id": 202,
      "options": {
        "minVizHeight": 75,
        "minVizWidth": 75,
        "orientation": "auto",
        "reduceOptions": {
          "calcs": [
            "lastNotNull"
          ],
          "fields": "",
          "values": false
        },
        "showThresholdLabels": false,
        "showThresholdMarkers": true,
        "sizing": "auto"
      },
      "pluginVersion": "12.3.0",
      "targets": [
        {
          "datasource": {
            "type": "prometheus",
            "uid": "prometheus"
          },
          "expr": "nginx_connections_active",
          "legendFormat": "Active Connections",
          "refId": "A"
        }
      ],
      "title": "⚡ Saturation (Active Connections)",
      "type": "gauge"
    },
    {
      "datasource": {
        "type": "prometheus",
        "uid": "prometheus"
      },
      "description": "**Why Monitor This?**\nAccepted vs handled connection ratio reveals if Nginx is dropping connections due to resource limits. Drops indicate saturation and potential user experience issues.\n\n**What It Measures:**\nTotal number of accepted and handled connections. Difference between accepted and handled indicates dropped connections.",
      "fieldConfig": {
        "defaults": {
          "color": {
            "mode": "thresholds"
          },
          "mappings": [],
          "thresholds": {
            "mode": "absolute",
            "steps": [
              {
                "color": "green",
                "value": null
              },
              {
                "color": "yellow",
                "value": 95
              },
              {
                "color": "green",
                "value": 99
              }
            ]
          },
          "unit": "percent",
          "max": 100,
          "min": 0
        },
        "overrides": []
      },
      "gridPos": {
        "h": 8,
        "w": 6,
        "x": 18,
        "y": 1
      },
      "id": 203,
      "options": {
        "minVizHeight": 75,
        "minVizWidth": 75,
        "orientation": "auto",
        "reduceOptions": {
          "calcs": [
            "lastNotNull"
          ],
          "fields": "",
          "values": false
        },
        "showThresholdLabels": false,
        "showThresholdMarkers": true,
        "sizing": "auto"
      },
      "pluginVersion": "12.3.0",
      "targets": [
        {
          "datasource": {
            "type": "prometheus",
            "uid": "prometheus"
          },
          "expr": "(rate(nginx_connections_handled[5m]) / rate(nginx_connections_accepted[5m])) * 100",
          "legendFormat": "Connection Success Rate",
          "refId": "A"
        }
      ],
      "title": "✅ Connection Success Rate %",
      "type": "gauge"
    },
    {
      "datasource": {
        "type": "prometheus",
        "uid": "prometheus"
      },
      "description": "**Why Monitor This? (SRE Perspective)**\n\nWaiting connections reveal important insights about your frontend's keep-alive configuration and connection management:\n\n**1. Keep-Alive Efficiency:** Idle connections waiting for the next request indicate that HTTP keep-alive is working. This reduces latency by reusing connections.\n\n**2. Connection Pool Health:** The ratio of waiting vs. active connections shows efficiency. Too many waiting connections may indicate:\n   - Misconfigured keep-alive timeout (too long)\n   - Connection leaks\n   - Need to tune worker_connections limits\n\n**3. Resource Planning:** Each idle connection consumes memory. Monitor trends to optimize keep-alive settings for balance between performance and resource usage.\n\n**4. Anomaly Detection:** Sudden spikes in waiting connections may indicate slow clients, DDoS attempts, or application issues.\n\n**What It Measures:**\n- **Waiting Connections:** Idle keep-alive connections waiting for next request\n- **Trend:** Sparkline shows changes over time\n- **Efficiency:** Percentage shown indicates connection reuse rate\n\n**Healthy Range:** 0-50 is normal; >100 may need investigation.",
      "fieldConfig": {
        "defaults": {
          "color": {
            "mode": "thresholds"
          },
          "mappings": [],
          "thresholds": {
            "mode": "absolute",
            "steps": [
              {
                "color": "green",
                "value": null
              },
              {
                "color": "yellow",
                "value": 50
              },
              {
                "color": "orange",
                "value": 100
              },
              {
                "color": "red",
                "value": 200
              }
            ]
          },
          "unit": "short"
        },
        "overrides": []
      },
      "gridPos": {
        "h": 8,
        "w": 6,
        "x": 6,
        "y": 11
      },
      "id": 204,
      "options": {
        "colorMode": "value",
        "graphMode": "area",
        "justifyMode": "auto",
        "orientation": "auto",
        "reduceOptions": {
          "values": false,
          "calcs": [
            "lastNotNull"
          ],
          "fields": ""
        },
        "textMode": "value_and_name",
        "showPercentChange": false
      },
      "pluginVersion": "10.0.0",
      "targets": [
        {
          "datasource": {
            "type": "prometheus",
            "uid": "prometheus"
          },
          "expr": "nginx_connections_waiting",
          "legendFormat": "Waiting Connections",
          "refId": "A"
        }
      ],
      "title": "⏳ Keep-Alive Connections (Waiting)",
      "type": "stat"
    },
    {
      "collapsed": false,
      "gridPos": {
        "h": 1,
        "w": 24,
        "x": 0,
        "y": 9
      },
      "id": 205,
      "panels": [],
      "title": "📊 Frontend Detailed Metrics",
      "type": "row"
    },
    {
      "datasource": {
        "type": "prometheus",
        "uid": "prometheus"
      },
      "description": "**Why Monitor This?**\nTracking latency percentiles over time helps identify performance degradation trends and the impact on different user segments. P50 shows typical experience, P95/P99 show worst-case scenarios.\n\n**What It Measures:**\nFrontend (Nginx) to Backend (Ktor) response time percentiles:\n- P50: Median user experience\n- P95: 95% of requests complete within this time\n- P99: 99% of requests (catches outliers)\n\n**Note:** Measures backend response time as seen from Nginx proxy.",
      "fieldConfig": {
        "defaults": {
          "color": {
            "mode": "palette-classic"
          },
          "custom": {
            "axisBorderShow": false,
            "axisCenteredZero": false,
            "axisColorMode": "text",
            "axisLabel": "",
            "axisPlacement": "auto",
            "barAlignment": 0,
            "barWidthFactor": 0.6,
            "drawStyle": "line",
            "fillOpacity": 10,
            "gradientMode": "none",
            "hideFrom": {
              "legend": false,
              "tooltip": false,
              "viz": false
            },
            "insertNulls": false,
            "lineInterpolation": "linear",
            "lineWidth": 2,
            "pointSize": 5,
            "scaleDistribution": {
              "type": "linear"
            },
            "showPoints": "never",
            "showValues": false,
            "spanNulls": false,
            "stacking": {
              "group": "A",
              "mode": "none"
            },
            "thresholdsStyle": {
              "mode": "off"
            }
          },
          "mappings": [],
          "thresholds": {
            "mode": "absolute",
            "steps": [
              {
                "color": "green",
                "value": 0
              }
            ]
          },
          "unit": "s"
        },
        "overrides": []
      },
      "gridPos": {
        "h": 8,
        "w": 12,
        "x": 0,
        "y": 10
      },
      "id": 211,
      "options": {
        "legend": {
          "calcs": [
            "mean",
            "max"
          ],
          "displayMode": "table",
          "placement": "bottom",
          "showLegend": true
        },
        "tooltip": {
          "hideZeros": false,
          "mode": "multi",
          "sort": "none"
        }
      },
      "pluginVersion": "12.3.0",
      "targets": [
        {
          "datasource": {
            "type": "prometheus",
            "uid": "prometheus"
          },
          "expr": "ktor_http_server_requests_seconds{quantile='0.5'} or vector(0)",
          "legendFormat": "P50 (Median)",
          "refId": "A"
        },
        {
          "datasource": {
            "type": "prometheus",
            "uid": "prometheus"
          },
          "expr": "ktor_http_server_requests_seconds{quantile='0.95'} or vector(0)",
          "legendFormat": "P95",
          "refId": "B"
        },
        {
          "datasource": {
            "type": "prometheus",
            "uid": "prometheus"
          },
          "expr": "ktor_http_server_requests_seconds{quantile='0.99'} or vector(0)",
          "legendFormat": "P99",
          "refId": "C"
        }
      ],
      "title": "Frontend→Backend Latency Percentiles",
      "type": "timeseries"
    },
    {
      "datasource": {
        "type": "prometheus",
        "uid": "prometheus"
      },
      "description": "**Why Monitor This?**\nAverage response time provides a simple overall health indicator. Sudden increases indicate performance issues affecting all users.\n\n**What It Measures:**\nAverage (mean) response time for requests proxied through Nginx to the backend. This is the total request processing time from Nginx's perspective.",
      "fieldConfig": {
        "defaults": {
          "color": {
            "mode": "palette-classic"
          },
          "custom": {
            "axisBorderShow": false,
            "axisCenteredZero": false,
            "axisColorMode": "text",
            "axisLabel": "",
            "axisPlacement": "auto",
            "barAlignment": 0,
            "barWidthFactor": 0.6,
            "drawStyle": "line",
            "fillOpacity": 10,
            "gradientMode": "none",
            "hideFrom": {
              "legend": false,
              "tooltip": false,
              "viz": false
            },
            "insertNulls": false,
            "lineInterpolation": "linear",
            "lineWidth": 2,
            "pointSize": 5,
            "scaleDistribution": {
              "type": "linear"
            },
            "showPoints": "never",
            "showValues": false,
            "spanNulls": false,
            "stacking": {
              "group": "A",
              "mode": "none"
            },
            "thresholdsStyle": {
              "mode": "line"
            }
          },
          "mappings": [],
          "thresholds": {
            "mode": "absolute",
            "steps": [
              {
                "color": "green",
                "value": 0
              },
              {
                "color": "red",
                "value": 0.5
              }
            ]
          },
          "unit": "s"
        },
        "overrides": []
      },
      "gridPos": {
        "h": 8,
        "w": 12,
        "x": 12,
        "y": 10
      },
      "id": 212,
      "options": {
        "legend": {
          "calcs": [
            "mean",
            "max"
          ],
          "displayMode": "table",
          "placement": "bottom",
          "showLegend": true
        },
        "tooltip": {
          "hideZeros": false,
          "mode": "multi",
          "sort": "none"
        }
      },
      "pluginVersion": "12.3.0",
      "targets": [
        {
          "datasource": {
            "type": "prometheus",
            "uid": "prometheus"
          },
          "expr": "sum(rate(ktor_http_server_requests_seconds_sum[5m])) / sum(rate(ktor_http_server_requests_seconds_count[5m]))",
          "legendFormat": "Average Response Time",
          "refId": "A"
        }
      ],
      "title": "Frontend→Backend Average Response Time",
      "type": "timeseries"
    },
    {
      "datasource": {
        "type": "prometheus",
        "uid": "prometheus"
      },
      "description": "**Why Monitor This?**\nTrends in request rate help identify patterns, predict capacity needs, and detect anomalies like DDoS attacks or traffic drops due to outages.\n\n**What It Measures:**\nHTTP request rate over time from Nginx.",
      "fieldConfig": {
        "defaults": {
          "color": {
            "mode": "palette-classic"
          },
          "custom": {
            "axisCenteredZero": false,
            "axisColorMode": "text",
            "axisLabel": "",
            "axisPlacement": "auto",
            "barAlignment": 0,
            "drawStyle": "line",
            "fillOpacity": 20,
            "gradientMode": "opacity",
            "hideFrom": {
              "tooltip": false,
              "viz": false,
              "legend": false
            },
            "lineInterpolation": "smooth",
            "lineWidth": 2,
            "pointSize": 5,
            "scaleDistribution": {
              "type": "linear"
            },
            "showPoints": "never",
            "spanNulls": false,
            "stacking": {
              "group": "A",
              "mode": "none"
            },
            "thresholdsStyle": {
              "mode": "off"
            }
          },
          "mappings": [],
          "thresholds": {
            "mode": "absolute",
            "steps": [
              {
                "color": "green",
                "value": null
              }
            ]
          },
          "unit": "reqps"
        },
        "overrides": []
      },
      "gridPos": {
        "h": 8,
        "w": 12,
        "x": 0,
        "y": 19
      },
      "id": 206,
      "options": {
        "legend": {
          "calcs": [
            "mean",
            "max",
            "last"
          ],
          "displayMode": "table",
          "placement": "bottom",
          "showLegend": true
        },
        "tooltip": {
          "mode": "multi",
          "sort": "none"
        }
      },
      "targets": [
        {
          "datasource": {
            "type": "prometheus",
            "uid": "prometheus"
          },
          "expr": "rate(nginx_http_requests_total[5m])",
          "legendFormat": "Request Rate",
          "refId": "A"
        }
      ],
      "title": "Frontend Request Rate Over Time",
      "type": "timeseries"
    },
    {
      "datasource": {
        "type": "prometheus",
        "uid": "prometheus"
      },
      "description": "**Why Monitor This?**\nConnection state distribution reveals bottlenecks. High 'reading' suggests slow clients, high 'writing' indicates slow responses or large payloads, high 'waiting' shows keep-alive usage.\n\n**What It Measures:**\n- Reading: Connections reading request headers\n- Writing: Connections sending responses to clients\n- Waiting: Idle keep-alive connections",
      "fieldConfig": {
        "defaults": {
          "color": {
            "mode": "palette-classic"
          },
          "custom": {
            "axisCenteredZero": false,
            "axisColorMode": "text",
            "axisLabel": "",
            "axisPlacement": "auto",
            "barAlignment": 0,
            "drawStyle": "line",
            "fillOpacity": 20,
            "gradientMode": "opacity",
            "hideFrom": {
              "tooltip": false,
              "viz": false,
              "legend": false
            },
            "lineInterpolation": "smooth",
            "lineWidth": 2,
            "pointSize": 5,
            "scaleDistribution": {
              "type": "linear"
            },
            "showPoints": "never",
            "spanNulls": false,
            "stacking": {
              "group": "A",
              "mode": "normal"
            },
            "thresholdsStyle": {
              "mode": "off"
            }
          },
          "mappings": [],
          "thresholds": {
            "mode": "absolute",
            "steps": [
              {
                "color": "green",
                "value": null
              }
            ]
          },
          "unit": "short"
        },
        "overrides": [
          {
            "matcher": {
              "id": "byName",
              "options": "Reading"
            },
            "properties": [
              {
                "id": "color",
                "value": {
                  "fixedColor": "blue",
                  "mode": "fixed"
                }
              }
            ]
          },
          {
            "matcher": {
              "id": "byName",
              "options": "Writing"
            },
            "properties": [
              {
                "id": "color",
                "value": {
                  "fixedColor": "green",
                  "mode": "fixed"
                }
              }
            ]
          },
          {
            "matcher": {
              "id": "byName",
              "options": "Waiting"
            },
            "properties": [
              {
                "id": "color",
                "value": {
                  "fixedColor": "orange",
                  "mode": "fixed"
                }
              }
            ]
          }
        ]
      },
      "gridPos": {
        "h": 8,
        "w": 12,
        "x": 12,
        "y": 19
      },
      "id": 207,
      "options": {
        "legend": {
          "calcs": [
            "mean",
            "max",
            "last"
          ],
          "displayMode": "table",
          "placement": "bottom",
          "showLegend": true
        },
        "tooltip": {
          "mode": "multi",
          "sort": "none"
        }
      },
      "targets": [
        {
          "datasource": {
            "type": "prometheus",
            "uid": "prometheus"
          },
          "expr": "nginx_connections_reading",
          "legendFormat": "Reading",
          "refId": "A"
        },
        {
          "datasource": {
            "type": "prometheus",
            "uid": "prometheus"
          },
          "expr": "nginx_connections_writing",
          "legendFormat": "Writing",
          "refId": "B"
        },
        {
          "datasource": {
            "type": "prometheus",
            "uid": "prometheus"
          },
          "expr": "nginx_connections_waiting",
          "legendFormat": "Waiting",
          "refId": "C"
        }
      ],
      "title": "Connection States (Reading/Writing/Waiting)",
      "type": "timeseries"
    },
    {
      "datasource": {
        "type": "prometheus",
        "uid": "prometheus"
      },
      "description": "**Why Monitor This?**\nActive connections trend indicates overall system load and helps with capacity planning. Sudden spikes may indicate attacks or viral traffic.\n\n**What It Measures:**\nTotal active connections to Nginx frontend over time.",
      "fieldConfig": {
        "defaults": {
          "color": {
            "mode": "palette-classic"
          },
          "custom": {
            "axisCenteredZero": false,
            "axisColorMode": "text",
            "axisLabel": "",
            "axisPlacement": "auto",
            "barAlignment": 0,
            "drawStyle": "line",
            "fillOpacity": 20,
            "gradientMode": "opacity",
            "hideFrom": {
              "tooltip": false,
              "viz": false,
              "legend": false
            },
            "lineInterpolation": "smooth",
            "lineWidth": 2,
            "pointSize": 5,
            "scaleDistribution": {
              "type": "linear"
            },
            "showPoints": "never",
            "spanNulls": false,
            "stacking": {
              "group": "A",
              "mode": "none"
            },
            "thresholdsStyle": {
              "mode": "line"
            }
          },
          "mappings": [],
          "thresholds": {
            "mode": "absolute",
            "steps": [
              {
                "color": "green",
                "value": null
              },
              {
                "color": "yellow",
                "value": 100
              },
              {
                "color": "red",
                "value": 200
              }
            ]
          },
          "unit": "short"
        },
        "overrides": []
      },
      "gridPos": {
        "h": 8,
        "w": 12,
        "x": 0,
        "y": 19
      },
      "id": 208,
      "options": {
        "legend": {
          "calcs": [
            "mean",
            "max",
            "last"
          ],
          "displayMode": "table",
          "placement": "bottom",
          "showLegend": true
        },
        "tooltip": {
          "mode": "multi",
          "sort": "none"
        }
      },
      "targets": [
        {
          "datasource": {
            "type": "prometheus",
            "uid": "prometheus"
          },
          "expr": "nginx_connections_active",
          "legendFormat": "Active Connections",
          "refId": "A"
        }
      ],
      "title": "Active Connections Over Time",
      "type": "timeseries"
    },
    {
      "datasource": {
        "type": "prometheus",
        "uid": "prometheus"
      },
      "description": "**Why Monitor This?**\nComparing accepted vs handled connections reveals if Nginx is operating at capacity. Dropped connections (accepted - handled) indicate resource exhaustion requiring immediate attention.\n\n**What It Measures:**\n- Accepted: Total connections accepted by Nginx\n- Handled: Total connections successfully handled\n- Gap indicates dropped connections",
      "fieldConfig": {
        "defaults": {
          "color": {
            "mode": "palette-classic"
          },
          "custom": {
            "axisCenteredZero": false,
            "axisColorMode": "text",
            "axisLabel": "",
            "axisPlacement": "auto",
            "barAlignment": 0,
            "drawStyle": "line",
            "fillOpacity": 10,
            "gradientMode": "none",
            "hideFrom": {
              "tooltip": false,
              "viz": false,
              "legend": false
            },
            "lineInterpolation": "smooth",
            "lineWidth": 2,
            "pointSize": 5,
            "scaleDistribution": {
              "type": "linear"
            },
            "showPoints": "never",
            "spanNulls": false,
            "stacking": {
              "group": "A",
              "mode": "none"
            },
            "thresholdsStyle": {
              "mode": "off"
            }
          },
          "mappings": [],
          "thresholds": {
            "mode": "absolute",
            "steps": [
              {
                "color": "green",
                "value": null
              }
            ]
          },
          "unit": "cps"
        },
        "overrides": [
          {
            "matcher": {
              "id": "byName",
              "options": "Accepted"
            },
            "properties": [
              {
                "id": "color",
                "value": {
                  "fixedColor": "blue",
                  "mode": "fixed"
                }
              }
            ]
          },
          {
            "matcher": {
              "id": "byName",
              "options": "Handled"
            },
            "properties": [
              {
                "id": "color",
                "value": {
                  "fixedColor": "green",
                  "mode": "fixed"
                }
              }
            ]
          }
        ]
      },
      "gridPos": {
        "h": 8,
        "w": 12,
        "x": 12,
        "y": 19
      },
      "id": 209,
      "options": {
        "legend": {
          "calcs": [
            "mean",
            "max",
            "last"
          ],
          "displayMode": "table",
          "placement": "bottom",
          "showLegend": true
        },
        "tooltip": {
          "mode": "multi",
          "sort": "none"
        }
      },
      "targets": [
        {
          "datasource": {
            "type": "prometheus",
            "uid": "prometheus"
          },
          "expr": "rate(nginx_connections_accepted[5m])",
          "legendFormat": "Accepted",
          "refId": "A"
        },
        {
          "datasource": {
            "type": "prometheus",
            "uid": "prometheus"
          },
          "expr": "rate(nginx_connections_handled[5m])",
          "legendFormat": "Handled",
          "refId": "B"
        }
      ],
      "title": "Accepted vs Handled Connections",
      "type": "timeseries"
    },
    {
      "datasource": {
        "type": "prometheus",
        "uid": "prometheus"
      },
      "description": "**Why Monitor This? (SRE Perspective)**\n\nTraffic is one of the Four Golden Signals and a critical SRE metric. Monitoring request rate helps:\n\n**1. Capacity Planning:** Understand current load to predict when scaling is needed before saturation occurs.\n\n**2. Anomaly Detection:** Sudden drops indicate outages or upstream failures; unexpected spikes may signal DDoS attacks or viral events.\n\n**3. SLO/SLI Tracking:** Traffic volume is essential context for interpreting error rates and latency (errors/traffic = error rate).\n\n**4. Business Metrics:** Request rate correlates with user activity and business health.\n\n**What It Measures:**\nTotal number of HTTP requests per second handled by the backend API.",
      "fieldConfig": {
        "defaults": {
          "color": {
            "mode": "thresholds"
          },
          "mappings": [],
          "thresholds": {
            "mode": "absolute",
            "steps": [
              {
                "color": "green",
                "value": null
              },
              {
                "color": "yellow",
                "value": 5
              },
              {
                "color": "red",
                "value": 10
              }
            ]
          },
          "unit": "reqps"
        },
        "overrides": []
      },
      "gridPos": {
        "h": 8,
        "w": 6,
        "x": 6,
        "y": 1
      },
      "id": 2,
      "options": {
        "orientation": "auto",
        "reduceOptions": {
          "values": false,
          "calcs": [
            "lastNotNull"
          ],
          "fields": ""
        },
        "showThresholdLabels": false,
        "showThresholdMarkers": true
      },
      "pluginVersion": "10.0.0",
      "targets": [
        {
          "datasource": {
            "type": "prometheus",
            "uid": "prometheus"
          },
          "expr": "sum(rate(ktor_http_server_requests_seconds_count[5m]))",
          "refId": "A"
        }
      ],
      "title": "📈 Traffic (Requests/sec)",
      "type": "gauge"
    },
    {
      "datasource": {
        "type": "prometheus",
        "uid": "prometheus"
      },
      "description": "**Why Monitor This? (SRE Perspective)**\n\nErrors are one of the Four Golden Signals and directly impact reliability and user trust. Monitoring error rates is critical for:\n\n**1. SLO/SLI Measurement:** Error rate is typically the most important SLO (e.g., \"99.9% of requests succeed\"). Breaching error budgets triggers incident response.\n\n**2. Rapid Incident Detection:** Spikes in 5xx errors indicate backend failures requiring immediate investigation.\n\n**3. User Experience:** Every error affects users and may cause data loss, failed transactions, or poor perception.\n\n**4. Change Validation:** Monitor error rates during deployments to catch regressions quickly.\n\n**What It Measures:**\nPercentage of requests returning 5xx server errors (failures caused by backend issues).",
      "fieldConfig": {
        "defaults": {
          "color": {
            "mode": "thresholds"
          },
          "mappings": [],
          "max": 10,
          "min": 0,
          "thresholds": {
            "mode": "absolute",
            "steps": [
              {
                "color": "green",
                "value": null
              },
              {
                "color": "yellow",
                "value": 0.5
              },
              {
                "color": "red",
                "value": 1
              }
            ]
          },
          "unit": "percent"
        },
        "overrides": []
      },
      "gridPos": {
        "h": 8,
        "w": 6,
        "x": 12,
        "y": 1
      },
      "id": 3,
      "options": {
        "orientation": "auto",
        "reduceOptions": {
          "values": false,
          "calcs": [
            "lastNotNull"
          ],
          "fields": ""
        },
        "showThresholdLabels": false,
        "showThresholdMarkers": true
      },
      "pluginVersion": "10.0.0",
      "targets": [
        {
          "datasource": {
            "type": "prometheus",
            "uid": "prometheus"
          },
          "expr": "((sum(rate(ktor_http_server_requests_seconds_count{status=~\"5..\"}[5m])) or vector(0)) / sum(rate(ktor_http_server_requests_seconds_count[5m]))) * 100",
          "refId": "A"
        }
      ],
      "title": "❌ Errors (5xx Error Rate %)",
      "type": "gauge"
    },
    {
      "datasource": {
        "type": "prometheus",
        "uid": "prometheus"
      },
      "description": "**Why Monitor This? (SRE Perspective)**\n\nSaturation is one of the Four Golden Signals and indicates how \"full\" your service is. CPU saturation monitoring is essential for:\n\n**1. Preventing Cascading Failures:** High CPU usage causes increased latency, timeouts, and eventually service crashes. Early detection prevents outages.\n\n**2. Capacity Planning:** Trend analysis shows when additional resources are needed before users are impacted.\n\n**3. Cost Optimization:** Right-sizing infrastructure based on actual utilization prevents over-provisioning.\n\n**4. Performance Baseline:** Abnormal CPU spikes indicate inefficient code, memory leaks, or unexpected workloads.\n\n**What It Measures:**\nCPU utilization percentage (100% - idle time) across all cores.",
      "fieldConfig": {
        "defaults": {
          "color": {
            "mode": "thresholds"
          },
          "mappings": [],
          "max": 100,
          "min": 0,
          "thresholds": {
            "mode": "absolute",
            "steps": [
              {
                "color": "green",
                "value": null
              },
              {
                "color": "yellow",
                "value": 70
              },
              {
                "color": "red",
                "value": 85
              }
            ]
          },
          "unit": "percent"
        },
        "overrides": []
      },
      "gridPos": {
        "h": 8,
        "w": 6,
        "x": 18,
        "y": 1
      },
      "id": 4,
      "options": {
        "orientation": "auto",
        "reduceOptions": {
          "values": false,
          "calcs": [
            "lastNotNull"
          ],
          "fields": ""
        },
        "showThresholdLabels": false,
        "showThresholdMarkers": true
      },
      "pluginVersion": "10.0.0",
      "targets": [
        {
          "datasource": {
            "type": "prometheus",
            "uid": "prometheus"
          },
          "expr": "100 - (avg(rate(node_cpu_seconds_total{mode=\"idle\"}[5m])) * 100)",
          "legendFormat": "CPU",
          "refId": "A"
        }
      ],
      "title": "⚡ Saturation (CPU Usage %)",
      "type": "gauge"
    },
    {
      "collapsed": false,
      "gridPos": {
        "h": 1,
        "w": 24,
        "x": 0,
        "y": 36
      },
      "id": 105,
      "panels": [],
      "title": "💽 Backend",
      "type": "row"
    },
    {
      "datasource": {
        "type": "prometheus",
        "uid": "prometheus"
      },
      "description": "**Why Monitor This? (SRE Perspective)**\n\nBreaking down traffic by status code provides actionable insights for SRE work:\n\n**1. Incident Triage:** Quickly distinguish between client errors (4xx - user/config issues) and server errors (5xx - backend failures) to focus response efforts.\n\n**2. Deployment Validation:** Compare status code distribution before/after deployments to detect regressions.\n\n**3. Capacity Analysis:** High 2xx volume with low latency indicates healthy capacity; high 2xx with high latency suggests approaching limits.\n\n**4. Security Monitoring:** Unusual patterns in 4xx errors may indicate attacks (e.g., high 401/403 from authentication failures).\n\n**What It Measures:**\nRequest rate over time broken down by HTTP status code categories (2xx success, 4xx client errors, 5xx server errors).",
      "fieldConfig": {
        "defaults": {
          "color": {
            "mode": "palette-classic"
          },
          "custom": {
            "axisBorderShow": false,
            "axisCenteredZero": false,
            "axisColorMode": "text",
            "axisLabel": "",
            "axisPlacement": "auto",
            "barAlignment": 0,
            "barWidthFactor": 0.6,
            "drawStyle": "line",
            "fillOpacity": 0,
            "gradientMode": "none",
            "hideFrom": {
              "legend": false,
              "tooltip": false,
              "viz": false
            },
            "insertNulls": false,
            "lineInterpolation": "linear",
            "lineWidth": 2,
            "pointSize": 5,
            "scaleDistribution": {
              "type": "linear"
            },
            "showPoints": "auto",
            "showValues": false,
            "spanNulls": false,
            "stacking": {
              "group": "A",
              "mode": "none"
            },
            "thresholdsStyle": {
              "mode": "off"
            }
          },
          "mappings": [],
          "thresholds": {
            "mode": "absolute",
            "steps": [
              {
                "color": "green",
                "value": 0
              },
              {
                "color": "red",
                "value": 80
              }
            ]
          },
          "unit": "s"
        },
        "overrides": []
      },
      "gridPos": {
        "h": 8,
        "w": 12,
        "x": 0,
        "y": 37
      },
      "id": 106,
      "options": {
        "legend": {
          "calcs": [],
          "displayMode": "table",
          "placement": "right",
          "showLegend": true
        },
        "tooltip": {
          "hideZeros": false,
          "mode": "single",
          "sort": "none"
        }
      },
      "pluginVersion": "12.3.0",
      "targets": [
        {
          "editorMode": "code",
          "expr": "ktor_http_server_requests_seconds{\r\n  quantile=\"0.95\",\r\n  route!~\"/health|/metrics-micrometer\"\r\n}\r\n",
          "legendFormat": "{{method}}: {{route}} ({{instance}})",
          "range": true,
          "refId": "A"
        }
      ],
      "title": "Latency – p95 by Route",
      "type": "timeseries"
    },
    {
      "datasource": {
        "type": "prometheus",
        "uid": "prometheus"
      },
      "fieldConfig": {
        "defaults": {
          "color": {
            "mode": "palette-classic"
          },
          "custom": {
            "axisBorderShow": false,
            "axisCenteredZero": false,
            "axisColorMode": "text",
            "axisLabel": "",
            "axisPlacement": "auto",
            "barAlignment": 0,
            "barWidthFactor": 0.5,
            "drawStyle": "bars",
            "fillOpacity": 0,
            "gradientMode": "opacity",
            "hideFrom": {
              "legend": false,
              "tooltip": false,
              "viz": false
            },
            "insertNulls": false,
            "lineInterpolation": "linear",
            "lineStyle": {
              "fill": "solid"
            },
            "lineWidth": 10,
            "pointSize": 5,
            "scaleDistribution": {
              "type": "linear"
            },
            "showPoints": "auto",
            "showValues": true,
            "spanNulls": true,
            "stacking": {
              "group": "A",
              "mode": "none"
            },
            "thresholdsStyle": {
              "mode": "off"
            }
          },
          "mappings": [],
          "thresholds": {
            "mode": "absolute",
            "steps": [
              {
                "color": "green",
                "value": 0
              },
              {
                "color": "red",
                "value": 80
              }
            ]
          },
          "unit": "reqps"
        },
        "overrides": []
      },
      "gridPos": {
        "h": 8,
        "w": 12,
        "x": 12,
        "y": 37
      },
      "id": 107,
      "options": {
        "legend": {
          "calcs": [],
          "displayMode": "list",
          "placement": "bottom",
          "showLegend": true
        },
        "tooltip": {
          "hideZeros": false,
          "mode": "single",
          "sort": "none"
        }
      },
      "pluginVersion": "12.3.0",
      "targets": [
        {
          "editorMode": "code",
          "expr": "sum(\r\n  rate(ktor_http_server_requests_seconds_count[1m])\r\n)\r\n",
          "legendFormat": "RPS",
          "range": true,
          "refId": "A"
        },
        {
          "datasource": {
            "type": "prometheus",
            "uid": "prometheus"
          },
          "expr": "sum(rate(ktor_http_server_requests_seconds_count{status=~\"4..\"}[5m]))",
          "legendFormat": "4xx (Client Error)",
          "refId": "B"
        },
        {
          "datasource": {
            "type": "prometheus",
            "uid": "prometheus"
          },
          "expr": "sum(rate(ktor_http_server_requests_seconds_count{status=~\"5..\"}[5m]))",
          "legendFormat": "5xx (Server Error)",
          "refId": "C"
        }
      ],
      "title": "RPS by Route",
      "type": "timeseries"
    },
    {
      "datasource": {
        "type": "prometheus",
        "uid": "prometheus"
      },
      "fieldConfig": {
        "defaults": {
          "color": {
            "mode": "palette-classic"
          },
          "custom": {
            "axisBorderShow": false,
            "axisCenteredZero": false,
            "axisColorMode": "text",
            "axisLabel": "",
            "axisPlacement": "auto",
            "barAlignment": 0,
            "barWidthFactor": 0.6,
            "drawStyle": "line",
            "fillOpacity": 0,
            "gradientMode": "none",
            "hideFrom": {
              "legend": false,
              "tooltip": false,
              "viz": false
            },
            "insertNulls": false,
            "lineInterpolation": "linear",
            "lineWidth": 1,
            "pointSize": 5,
            "scaleDistribution": {
              "type": "linear"
            },
            "showPoints": "auto",
            "showValues": false,
            "spanNulls": false,
            "stacking": {
              "group": "A",
              "mode": "none"
            },
            "thresholdsStyle": {
              "mode": "off"
            }
          },
          "mappings": [],
          "thresholds": {
            "mode": "absolute",
            "steps": [
              {
                "color": "green",
                "value": 0
              },
              {
                "color": "red",
                "value": 80
              }
            ]
          }
        },
        "overrides": []
      },
      "gridPos": {
        "h": 8,
        "w": 12,
        "x": 12,
        "y": 45
      },
      "id": 110,
      "options": {
        "legend": {
          "calcs": [],
          "displayMode": "list",
          "placement": "bottom",
          "showLegend": true
        },
        "tooltip": {
          "hideZeros": false,
          "mode": "single",
          "sort": "none"
        }
      },
      "pluginVersion": "12.3.0",
      "targets": [
        {
          "datasource": {
            "type": "prometheus",
            "uid": "prometheus"
          },
          "expr": "(sum(rate(ktor_http_server_requests_seconds_count{status=~\"5..\"}[5m])) / sum(rate(ktor_http_server_requests_seconds_count[5m]))) * 100",
          "legendFormat": "Error Rate (5xx)",
          "refId": "A"
        }
      ],
      "title": "Error Percentage (5xx)",
      "type": "timeseries"
    },
    {
      "datasource": {
        "type": "prometheus",
        "uid": "prometheus"
      },
      "fieldConfig": {
        "defaults": {
          "color": {
            "mode": "palette-classic"
          },
          "custom": {
            "axisBorderShow": false,
            "axisCenteredZero": false,
            "axisColorMode": "text",
            "axisLabel": "",
            "axisPlacement": "auto",
            "barAlignment": 0,
            "barWidthFactor": 0.6,
            "drawStyle": "line",
            "fillOpacity": 0,
            "gradientMode": "none",
            "hideFrom": {
              "legend": false,
              "tooltip": false,
              "viz": false
            },
            "insertNulls": false,
            "lineInterpolation": "linear",
            "lineWidth": 1,
            "pointSize": 5,
            "scaleDistribution": {
              "type": "linear"
            },
            "showPoints": "auto",
            "showValues": false,
            "spanNulls": false,
            "stacking": {
              "group": "A",
              "mode": "none"
            },
            "thresholdsStyle": {
              "mode": "off"
            }
          },
          "mappings": [],
          "thresholds": {
            "mode": "absolute",
            "steps": [
              {
                "color": "green",
                "value": 0
              },
              {
                "color": "red",
                "value": 80
              }
            ]
          }
        },
        "overrides": []
      },
      "gridPos": {
        "h": 8,
        "w": 12,
        "x": 0,
        "y": 53
      },
      "id": 109,
      "options": {
        "legend": {
          "calcs": [],
          "displayMode": "list",
          "placement": "bottom",
          "showLegend": true
        },
        "tooltip": {
          "hideZeros": false,
          "mode": "single",
          "sort": "none"
        }
      },
      "pluginVersion": "12.3.0",
      "targets": [
        {
          "editorMode": "code",
          "expr": "sum(\r\n  rate(ktor_http_server_requests_seconds_count{status=~\"5..\"}[1m])\r\n)\r\n",
          "legendFormat": "__auto",
          "range": true,
          "refId": "A"
        }
      ],
      "title": "Error Rate (5xx)",
      "type": "timeseries"
    },
    {
      "datasource": {
        "type": "prometheus",
        "uid": "prometheus"
      },
      "description": "",
      "fieldConfig": {
        "defaults": {
          "color": {
            "mode": "palette-classic"
          },
          "custom": {
            "axisBorderShow": false,
            "axisCenteredZero": false,
            "axisColorMode": "text",
            "axisLabel": "",
            "axisPlacement": "auto",
            "barAlignment": 0,
            "barWidthFactor": 0.6,
            "drawStyle": "line",
            "fillOpacity": 0,
            "gradientMode": "none",
            "hideFrom": {
              "legend": false,
              "tooltip": false,
              "viz": false
            },
            "insertNulls": false,
            "lineInterpolation": "linear",
            "lineWidth": 1,
            "pointSize": 5,
            "scaleDistribution": {
              "type": "linear"
            },
            "showPoints": "auto",
            "showValues": false,
            "spanNulls": false,
            "stacking": {
              "group": "A",
              "mode": "none"
            },
            "thresholdsStyle": {
              "mode": "off"
            }
          },
          "mappings": [],
          "thresholds": {
            "mode": "absolute",
            "steps": [
              {
                "color": "green",
                "value": 0
              },
              {
                "color": "red",
                "value": 80
              }
            ]
          }
        },
        "overrides": []
      },
      "gridPos": {
        "h": 8,
        "w": 12,
        "x": 12,
        "y": 53
      },
      "id": 111,
      "options": {
        "legend": {
          "calcs": [],
          "displayMode": "list",
          "placement": "bottom",
          "showLegend": true
        },
        "tooltip": {
          "hideZeros": false,
          "mode": "single",
          "sort": "none"
        }
      },
      "pluginVersion": "12.3.0",
      "targets": [
        {
          "editorMode": "code",
          "expr": "sum by (route, status)(\r\n  rate(ktor_http_server_requests_seconds_count{status=~\"4..|5..\"}[1m])\r\n)\r\n",
          "legendFormat": "__auto",
          "range": true,
          "refId": "A"
        }
      ],
      "title": "Errors by Route",
      "type": "timeseries"
    },
    {
      "datasource": {
        "type": "prometheus",
        "uid": "prometheus"
      },
      "fieldConfig": {
        "defaults": {
          "color": {
            "mode": "palette-classic"
          },
          "custom": {
            "axisBorderShow": false,
            "axisCenteredZero": false,
            "axisColorMode": "text",
            "axisLabel": "",
            "axisPlacement": "auto",
            "barAlignment": 0,
            "barWidthFactor": 0.6,
            "drawStyle": "bars",
            "fillOpacity": 0,
            "gradientMode": "hue",
            "hideFrom": {
              "legend": false,
              "tooltip": false,
              "viz": false
            },
            "insertNulls": false,
            "lineInterpolation": "linear",
            "lineStyle": {
              "fill": "solid"
            },
            "lineWidth": 10,
            "pointSize": 5,
            "scaleDistribution": {
              "type": "linear"
            },
            "showPoints": "auto",
            "showValues": false,
            "spanNulls": false,
            "stacking": {
              "group": "A",
              "mode": "none"
            },
            "thresholdsStyle": {
              "mode": "off"
            }
          },
          "mappings": [],
          "thresholds": {
            "mode": "absolute",
            "steps": [
              {
                "color": "green",
                "value": 0
              },
              {
                "color": "red",
                "value": 80
              }
            ]
          },
          "unit": "s"
        },
        "overrides": []
      },
      "gridPos": {
        "h": 8,
        "w": 12,
        "x": 0,
        "y": 61
      },
      "id": 112,
      "options": {
        "legend": {
          "calcs": [],
          "displayMode": "table",
          "placement": "right",
          "showLegend": true
        },
        "tooltip": {
          "hideZeros": false,
          "mode": "single",
          "sort": "none"
        }
      },
      "pluginVersion": "12.3.0",
      "targets": [
        {
          "datasource": {
            "type": "prometheus",
            "uid": "prometheus"
          },
          "expr": "(1 - (node_filesystem_avail_bytes{mountpoint=\"/\"} / node_filesystem_size_bytes{mountpoint=\"/\"})) * 100",
          "legendFormat": "Disk Usage",
          "refId": "A"
        }
      ],
      "title": "Avg Request Duration (Load Indicator)",
      "type": "timeseries"
    },
    {
      "collapsed": false,
      "gridPos": {
        "h": 1,
        "w": 24,
        "x": 0,
        "y": 69
      },
      "id": 104,
      "panels": [],
      "title": "🗄️ Database & Infrastructure Metrics",
      "type": "row"
    },
    {
      "datasource": {
        "type": "prometheus",
        "uid": "prometheus"
      },
      "fieldConfig": {
        "defaults": {
          "color": {
            "mode": "palette-classic"
          },
          "custom": {
            "axisBorderShow": false,
            "axisCenteredZero": false,
            "axisColorMode": "text",
            "axisLabel": "",
            "axisPlacement": "auto",
            "barAlignment": 0,
            "barWidthFactor": 0.6,
            "drawStyle": "line",
            "fillOpacity": 10,
            "gradientMode": "none",
            "hideFrom": {
              "legend": false,
              "tooltip": false,
              "viz": false
            },
            "insertNulls": false,
            "lineInterpolation": "linear",
            "lineWidth": 2,
            "pointSize": 5,
            "scaleDistribution": {
              "type": "linear"
            },
            "showPoints": "never",
            "showValues": false,
            "spanNulls": false,
            "stacking": {
              "group": "A",
              "mode": "none"
            },
            "thresholdsStyle": {
              "mode": "off"
            }
          },
          "mappings": [],
          "thresholds": {
            "mode": "absolute",
            "steps": [
              {
                "color": "green",
                "value": 0
              }
            ]
          },
          "unit": "short"
        },
        "overrides": []
      },
      "gridPos": {
        "h": 8,
        "w": 12,
        "x": 0,
        "y": 70
      },
      "id": 40,
      "options": {
        "legend": {
          "calcs": [
            "mean",
            "max"
          ],
          "displayMode": "table",
          "placement": "bottom",
          "showLegend": true
        },
        "tooltip": {
          "hideZeros": false,
          "mode": "multi",
          "sort": "none"
        }
      },
      "pluginVersion": "12.3.0",
      "targets": [
        {
          "datasource": {
            "type": "prometheus",
            "uid": "prometheus"
          },
          "expr": "mysql_global_status_threads_connected",
          "legendFormat": "Active Connections",
          "refId": "A"
        },
        {
          "datasource": {
            "type": "prometheus",
            "uid": "prometheus"
          },
          "expr": "mysql_global_status_threads_running",
          "legendFormat": "Running Threads",
          "refId": "B"
        }
      ],
      "title": "MySQL - Connection & Thread Activity",
      "type": "timeseries"
    },
    {
      "datasource": {
        "type": "prometheus",
        "uid": "prometheus"
      },
      "fieldConfig": {
        "defaults": {
          "color": {
            "mode": "palette-classic"
          },
          "custom": {
            "axisBorderShow": false,
            "axisCenteredZero": false,
            "axisColorMode": "text",
            "axisLabel": "",
            "axisPlacement": "auto",
            "barAlignment": 0,
            "barWidthFactor": 0.6,
            "drawStyle": "line",
            "fillOpacity": 10,
            "gradientMode": "none",
            "hideFrom": {
              "legend": false,
              "tooltip": false,
              "viz": false
            },
            "insertNulls": false,
            "lineInterpolation": "linear",
            "lineWidth": 2,
            "pointSize": 5,
            "scaleDistribution": {
              "type": "linear"
            },
            "showPoints": "never",
            "showValues": false,
            "spanNulls": false,
            "stacking": {
              "group": "A",
              "mode": "none"
            },
            "thresholdsStyle": {
              "mode": "off"
            }
          },
          "mappings": [],
          "thresholds": {
            "mode": "absolute",
            "steps": [
              {
                "color": "green",
                "value": 0
              }
            ]
          },
          "unit": "reqps"
        },
        "overrides": []
      },
      "gridPos": {
        "h": 8,
        "w": 12,
        "x": 12,
        "y": 70
      },
      "id": 41,
      "options": {
        "legend": {
          "calcs": [
            "mean",
            "max"
          ],
          "displayMode": "table",
          "placement": "bottom",
          "showLegend": true
        },
        "tooltip": {
          "hideZeros": false,
          "mode": "multi",
          "sort": "none"
        }
      },
      "pluginVersion": "12.3.0",
      "targets": [
        {
          "datasource": {
            "type": "prometheus",
            "uid": "prometheus"
          },
          "expr": "rate(nginx_http_requests_total[5m])",
          "legendFormat": "Nginx Requests/sec",
          "refId": "A"
        }
      ],
      "title": "Nginx - HTTP Request Rate",
      "type": "timeseries"
    }
  ],
  "preload": false,
  "refresh": "10s",
  "schemaVersion": 42,
  "tags": [
    "int531",
    "sre",
    "golden-signals",
    "monitoring"
  ],
  "templating": {
    "list": []
  },
  "time": {
    "from": "now-1h",
    "to": "now"
  },
  "timepicker": {},
  "timezone": "",
  "title": "INT531 - Four Golden Signals Dashboard",
  "uid": "int531-golden-signals",
  "version": 1
}